vgame/Z_bak_code.py
vgame/__init__.py
vgame/actor.py
vgame/controller.py
vgame/dijkstra.py
vgame/image.py
vgame/music.py
vgame/theater.py
vgame-0.1.10.dist-info/LICENSE
vgame-0.1.10.dist-info/METADATA
vgame-0.1.10.dist-info/WHEEL
vgame-0.1.10.dist-info/top_level.txt
vgame-0.1.10.dist-info/RECORD
