Metadata-Version: 2.1
Name: vgame
Version: 0.1.10
Summary: UNKNOWN
Home-page: https://github.com/cilame/vgame
Author: cilame
Author-email: opaquism@hotmail.com
License: MIT
Keywords: vgame
Platform: UNKNOWN
Classifier: License :: OSI Approved :: MIT License
Classifier: Programming Language :: Python
Classifier: Intended Audience :: Developers
Requires-Python: >=3.3
Requires-Dist: pygame
